{
  "Main": {
    "08:00": "Doors Open (PAC Lobby)",
    "08:30": "Opening Ceremony (PAC)",
    "09:00": "Breakfast & Team Making (Cafe)",
    "10:00": "Hacking begins",
    "12:00": "Lunch (Cafe)",
    "18:00": "Hacking ends AND Dinner (Cafe)",
    "19:00": "Judging Begins",
    "20:00": "Presentations and Award Ceremony (PAC)",
    "21:00": "Event Ends"
  },
  "Workshops (Room 701)": {
    "14:00": "Web Dev Workshop",
    "16:00": "Security Workshop"
  },
  "Activities": {
    "13:00": "Gimkit (Annex)",
    "15:00": "Mario Kart (Annex)"
  }
}
